blocksim_poetry_plugin/__init__.py
blocksim_poetry_plugin/plugin.py
blocksim_poetry_plugin-0.1.4.dist-info/entry_points.txt
blocksim_poetry_plugin-0.1.4.dist-info/LICENSE
blocksim_poetry_plugin-0.1.4.dist-info/WHEEL
blocksim_poetry_plugin-0.1.4.dist-info/METADATA
blocksim_poetry_plugin-0.1.4.dist-info/RECORD
