Metadata-Version: 2.1
Name: blocksim-poetry-plugin
Version: 0.1.4
Summary: A plugin for more poetry commands
Home-page: https://gitlab.com/manawenuz/blocksim-poetry-plugin
License: MIT
Author: John Gray
Author-email: manawenuz@johncloud.fr
Requires-Python: >=3.8,<3.11
Classifier: License :: OSI Approved :: MIT License
Classifier: Programming Language :: Python :: 3
Classifier: Programming Language :: Python :: 3.8
Classifier: Programming Language :: Python :: 3.9
Classifier: Programming Language :: Python :: 3.10
Classifier: Topic :: Software Development :: Build Tools
Classifier: Topic :: Software Development :: Libraries :: Python Modules
Requires-Dist: MarkupSafe (==2.0.1)
Requires-Dist: docutils (>=0.14,<0.18)
Requires-Dist: jinja2 (==2.11.3)
Requires-Dist: mock (>=4.0.3,<5.0.0)
Requires-Dist: sphinx (==3.3.1)
Requires-Dist: sphinx-autoapi (>=1.8.4,<2.0.0)
Requires-Dist: sphinx-gallery (>=0.10.0,<0.11.0)
Requires-Dist: sphinx_rtd_theme (>=1.0.0,<2.0.0)
Requires-Dist: sphinxcontrib-apidoc (>=0.3.0,<0.4.0)
Requires-Dist: sphinxcontrib-napoleon (>=0.7,<0.8)
Project-URL: Bug Tracker, https://gitlab.com/manawenuz/blocksim-poetry-plugin/issues
Project-URL: Repository, https://gitlab.com/manawenuz/blocksim-poetry-plugin
